harrpy/__init__.py
harrpy/cli.py
harrpy/harrpy.py
harrpy-0.1.0.dist-info/LICENSE
harrpy-0.1.0.dist-info/METADATA
harrpy-0.1.0.dist-info/WHEEL
harrpy-0.1.0.dist-info/entry_points.txt
harrpy-0.1.0.dist-info/top_level.txt
harrpy-0.1.0.dist-info/RECORD
